airtable_orm/__init__.py
airtable_orm/airtable_query.py
airtable_orm/airtable_session.py
airtable_orm-1.0.4.dist-info/METADATA
airtable_orm-1.0.4.dist-info/WHEEL
airtable_orm-1.0.4.dist-info/top_level.txt
airtable_orm-1.0.4.dist-info/RECORD
