Metadata-Version: 2.1
Name: airtable-orm
Version: 1.0.4
Summary: ORM for Airtable tables
Home-page: https://github.com/muthugit/airtable_python_orm
Author: Muthupandian
Author-email: contact@muthupandian.in
